README.md
setup.py
RepositoryChecker/RepositoryChecker.py
RepositoryChecker/__init__.py
RepositoryChecker.egg-info/PKG-INFO
RepositoryChecker.egg-info/SOURCES.txt
RepositoryChecker.egg-info/dependency_links.txt
RepositoryChecker.egg-info/top_level.txt