Metadata-Version: 2.1
Name: RepositoryChecker
Version: 0.0.2
Summary: Check repository and corect it with parametred actions
Home-page: https://github.com/Nydareld/RepositoryChecker
Author: Théo "Nydareld" Guerin
Author-email: theo.guerin.pro@gmail.com
License: UNKNOWN
Platform: UNKNOWN
Classifier: Programming Language :: Python :: 3.5
Classifier: Programming Language :: Python :: 3.6
Classifier: Programming Language :: Python :: 3.7
Classifier: License :: OSI Approved :: MIT License
Classifier: Operating System :: OS Independent
